{
  "annotations": {
    "changelogDate": "20240303123226"
  },
  "applications": "*",
  "changelogDate": "20240303123226",
  "dto": "no",
  "embedded": false,
  "entityTableName": "rating",
  "fields": [
    {
      "fieldName": "ratedAt",
      "fieldType": "Instant",
      "fieldValidateRules": ["required"]
    }
  ],
  "fluentMethods": true,
  "jpaMetamodelFiltering": false,
  "name": "Rating",
  "pagination": "no",
  "readOnly": false,
  "relationships": [
    {
      "otherEntityName": "user",
      "relationshipName": "userRated",
      "relationshipSide": "left",
      "relationshipType": "many-to-one"
    },
    {
      "otherEntityName": "outfit",
      "otherEntityRelationshipName": "ratings",
      "relationshipName": "outfit",
      "relationshipSide": "right",
      "relationshipType": "many-to-one"
    }
  ],
  "searchEngine": "no",
  "service": "no"
}
